{
    "boxShadow": "none",
    "widgetName": "Text1",
    "dynamicPropertyPathList": [{"key": "fontSize"}],
    "topRow": 0,
    "bottomRow": 4,
    "parentRowSpace": 40,
    "type": "TEXT_WIDGET",
    "parentColumnSpace": 53,
    "overflow": "NONE",
    "fontFamily": "System Default",
    "leftColumn": 0,
    "dynamicBindingPathList": [{"key": "text"}],
    "text": "<h2>Meeting {{fetch_event.data.status}}<\/h2>",
    "labelTextSize": "0.875rem",
    "rightColumn": 64,
    "textAlign": "CENTER",
    "dynamicHeight": "FIXED",
    "widgetId": "d2w36x1330",
    "isVisible": true,
    "fontStyle": "BOLD",
    "version": 1,
    "textColor": "#231F20",
    "parentId": "i1773na87x",
    "isLoading": false,
    "borderRadius": "0px",
    "maxDynamicHeight": 9000,
    "fontSize": "1.5rem",
    "minDynamicHeight": 4
}